goldie/__about__.py
goldie/__init__.py
goldie/comparison.py
goldie/diff.py
goldie/execution.py
goldie/testing.py
goldie/update.py
goldie/tests/__init__.py
goldie/tests/test_diff.py
goldie/tests/testdata/comparison-1.txt
goldie/tests/testdata/comparison-2.txt
goldie-0.1.8.dist-info/METADATA
goldie-0.1.8.dist-info/WHEEL
goldie-0.1.8.dist-info/licenses/LICENSE
goldie-0.1.8.dist-info/RECORD
