Metadata-Version: 2.4
Name: goldie
Version: 0.1.8
Summary: A humble library greasing the gears of golden file tests
Project-URL: Homepage, https://github.com/merschformann/goldie
Project-URL: Repository, https://github.com/merschformann/goldie
Author-email: Marius Merschformann <merschformann@proton.me>
Maintainer-email: Marius Merschformann <merschformann@proton.me>
License: MIT License
License-File: LICENSE
Keywords: golden file,integration test,test,testing
Classifier: License :: OSI Approved :: Apache Software License
Classifier: Operating System :: OS Independent
Classifier: Programming Language :: Python :: 3
Classifier: Programming Language :: Python :: 3.9
Classifier: Programming Language :: Python :: 3.10
Classifier: Programming Language :: Python :: 3.11
Classifier: Programming Language :: Python :: 3.12
Classifier: Programming Language :: Python :: 3.13
Requires-Python: >=3.9
Requires-Dist: jflat>=0.1.4
Provides-Extra: dev
Requires-Dist: ruff>=0.6.4; extra == 'dev'
